[
     {
          "name": "Бесконечное лето",
          "icon": "es.jpg",
          "vk": "https://vk.com/everlasting.summer.official",
          "steam": "https://store.steampowered.com/app/331470/Everlasting_Summer/",
          "alt": "false",
          "enabled": "true"
     },
     {
          "name": "Сообщество",
          "icon": "community.jpg",
          "vk": "https://vk.com/eso_la",
          "steam": "https://steamcommunity.com/sharedfiles/filedetails/?id=2811713757",
          "alt": "false",
          "enabled": "true"
     },
     {
          "name": "Бесконечное лето: Продолжение истории",
          "icon": "blpi.jpg",
          "vk": "https://vk.com/es.continue",
          "steam": "https://steamcommunity.com/sharedfiles/filedetails/?id=508932099",
          "alt": "false",
          "enabled": "true"
     },
     {
          "name": "7 Дней Лета: Конверсия",
          "icon": "7dlk.jpg",
          "vk": "https://vk.com/sanati_tales",
          "steam": "",
          "alt": "false",
          "enabled": "true"
     },
     {
          "name": "7 Дней Лета: Lost Alpha",
          "icon": "7dlla.jpg",
          "vk": "https://vk.com/bl_7dl",
          "steam": "https://steamcommunity.com/sharedfiles/filedetails/?id=441054187",
          "alt": "false",
          "enabled": "true"
     },
     {
          "name": "Дубликат",
          "icon": "dublicate.jpg",
          "vk": "https://vk.com/dublicatum",
          "steam": "https://steamcommunity.com/sharedfiles/filedetails/?id=1727878478",
          "alt": "false",
          "enabled": "true"
     },
     {
          "name": "В погоне за хвостиком",
          "icon": "tr.jpg",
          "vk": "https://vk.com/yulyamod",
          "steam": "https://steamcommunity.com/sharedfiles/filedetails/?id=1250096348",
          "alt": "false",
          "enabled": "true"
     },
     {
          "name": "Титанобоа",
          "icon": "titanboa.jpg",
          "vk": "https://vk.com/public155935762",
          "steam": "https://steamcommunity.com/sharedfiles/filedetails/?id=2522905701",
          "alt": "false",
          "enabled": "true"
     },
     {
          "name": "Настоящий лагерь",
          "icon": "realcamp.jpg",
          "vk": "https://vk.com/real_camp",
          "steam": "https://steamcommunity.com/sharedfiles/filedetails/?id=1782535372",
          "alt": "false",
          "enabled": "true"
     },
     {
          "name": "Саманта",
          "icon": "samanta.jpg",
          "vk": "https://vk.com/goodwill_embassy",
          "steam": "https://steamcommunity.com/sharedfiles/filedetails/?id=354397869",
          "alt": "false",
          "enabled": "true"
     },
     {
          "name": "Алеся: Побег из лагеря",
          "icon": "alesya.jpg",
          "vk": "https://vk.com/rerospective",
          "steam": "https://steamcommunity.com/sharedfiles/filedetails/?id=1498012318",
          "alt": "false",
          "enabled": "true"
     },
     {
          "name": "Булки, кефир и рок-н-ролл",
          "icon": "bkrr.jpg",
          "vk": "https://vk.com/b_k_r_r",
          "steam": "https://steamcommunity.com/sharedfiles/filedetails/?id=451835368",
          "alt": "false",
          "enabled": "true"
     },
     {
          "name": "1+1. Диана",
          "icon": "dianamod.gif",
          "vk": "https://vk.com/bl1plus1",
          "steam": "https://steamcommunity.com/sharedfiles/filedetails/?id=1402145998",
          "alt": "false",
          "enabled": "true"
     },
     {
          "name": "Бесконечный холод",
          "icon": "beskholod.jpg",
          "vk": "https://vk.com/everlasting_cold",
          "steam": "https://steamcommunity.com/sharedfiles/filedetails/?id=443822638",
          "alt": "false",
          "enabled": "true"
     },
     {
          "name": "Гости из будущего",
          "icon": "gftf.jpg",
          "vk": "https://vk.com/rerospective",
          "steam": "https://steamcommunity.com/sharedfiles/filedetails/?id=1923313309",
          "alt": "false",
          "enabled": "true"
     },
     {
          "name": "Холодные объятия",
          "icon": "coldhugs.jpg",
          "vk": "https://vk.com/signivaried",
          "steam": "https://steamcommunity.com/sharedfiles/filedetails/?id=1666671085",
          "alt": "false",
          "enabled": "true"
     },
     {
          "name": "Видение",
          "icon": "vision.jpg",
          "vk": "https://vk.com/thenodworld",
          "steam": "https://steamcommunity.com/sharedfiles/filedetails/?id=1697630634",
          "alt": "false",
          "enabled": "true"
     },
     {
          "name": "Грязное лето",
          "icon": "dirtysummer.jpg",
          "vk": "",
          "steam": "https://steamcommunity.com/sharedfiles/filedetails/?id=1565827676",
          "alt": "false",
          "enabled": "true"
     },
     {
          "name": "История одного лагеря",
          "icon": "ocs.jpg",
          "vk": "https://vk.com/club165523574",
          "steam": "https://steamcommunity.com/sharedfiles/filedetails/?id=2328900004",
          "alt": "false",
          "enabled": "true"
     },
     {
          "name": "Лето 87-го",
          "icon": "s87.jpg",
          "vk": "https://vk.com/summerof87",
          "steam": "https://steamcommunity.com/sharedfiles/filedetails/?id=2152105095",
          "alt": "false",
          "enabled": "true"
     },
     {
          "name": "Оставшаяся взаперти",
          "icon": "closen.jpg",
          "vk": "https://vk.com/unknownsteam",
          "steam": "https://steamcommunity.com/sharedfiles/filedetails/?id=2553146986",
          "alt": "false",
          "enabled": "true"
     },
     {
          "name": "Теория мультивселенной",
          "icon": "multeory.jpg",
          "vk": "https://vk.com/bft_group",
          "steam": "https://steamcommunity.com/sharedfiles/filedetails/?id=2418558168",
          "alt": "false",
          "enabled": "true"
     },
     {
          "name": "Чужой среди своих",
          "icon": "among.jpg",
          "vk": "",
          "steam": "https://steamcommunity.com/sharedfiles/filedetails/?id=2537799247",
          "alt": "false",
          "enabled": "true"
     },
     {
          "name": "Вспомнить всё",
          "icon": "forall.jpg",
          "vk": "https://vk.com/rem_all",
          "steam": "https://steamcommunity.com/sharedfiles/filedetails/?id=704832307",
          "alt": "false",
          "enabled": "true"
     },
     {
          "name": "По ту сторону совёнка",
          "icon": "otoside.jpg",
          "vk": "https://vk.com/redowlteam",
          "steam": "https://steamcommunity.com/sharedfiles/filedetails/?id=1632368158",
          "alt": "false",
          "enabled": "true"
     },
     {
          "name": "Совёнок для двоих",
          "icon": "oft.jpg",
          "vk": "https://vk.com/2sova",
          "steam": "https://steamcommunity.com/sharedfiles/filedetails/?id=1283643946",
          "alt": "false",
          "enabled": "true"
     },
     {
          "name": "Чистовик",
          "icon": "cc.jpg",
          "vk": "https://vk.com/chistovik_es",
          "steam": "https://steamcommunity.com/sharedfiles/filedetails/?id=1663475241",
          "alt": "false",
          "enabled": "true"
     },
     {
          "name": "Братское лето",
          "icon": "brothersummer.jpg",
          "vk": "https://vk.com/fraternalsummer",
          "steam": "https://steamcommunity.com/sharedfiles/filedetails/?id=2520468168",
          "alt": "false",
          "enabled": "true"
     },
     {
          "name": "Яна",
          "icon": "yana.jpg",
          "vk": "https://vk.com/zeroimpact",
          "steam": "https://steamcommunity.com/sharedfiles/filedetails/?id=2239853287",
          "alt": "false",
          "enabled": "true"
     },
     {
          "name": "Элемент системы",
          "icon": "eots.jpg",
          "vk": "https://vk.com/darrenwhitegroup",
          "steam": "https://steamcommunity.com/sharedfiles/filedetails/?id=1549580691",
          "alt": "false",
          "enabled": "true"
     },
     {
          "name": "Тень внутри",
          "icon": "shdowwithin.jpg",
          "vk": "https://vk.com/fallenangelteam",
          "steam": "https://steamcommunity.com/sharedfiles/filedetails/?id=2561165070",
          "alt": "false",
          "enabled": "true"
     },
     {
          "name": "Облака",
          "icon": "clouds.jpg",
          "vk": "https://vk.com/yoroshka",
          "steam": "https://steamcommunity.com/sharedfiles/filedetails/?id=1795089707",
          "alt": "false",
          "enabled": "true"
     },
     {
          "name": "Ламповое лето",
          "icon": "cozysummer.jpg",
          "vk": "https://vk.com/lampoleto",
          "steam": "https://steamcommunity.com/sharedfiles/filedetails/?id=2352104813",
          "alt": "false",
          "enabled": "true"
     },
     {
          "name": "Возвращение Семёна или Орден Совёнка",
          "icon": "rsos.jpg",
          "vk": "https://vk.com/herrainisstudio",
          "steam": "https://steamcommunity.com/sharedfiles/filedetails/?id=1649019361",
          "alt": "false",
          "enabled": "true"
     },
     {
          "name": "История одного неудачника",
          "icon": "ion.jpg",
          "vk": "https://vk.com/blackravenficbook",
          "steam": "https://steamcommunity.com/sharedfiles/filedetails/?id=1570626647",
          "alt": "false",
          "enabled": "true"
     }
]
